MANIFEST.in
README.rst
setup.py
docs/HISTORY.txt
docs/LICENSE.GPL
docs/LICENSE.txt
ftw/__init__.py
ftw.profilehook.egg-info/PKG-INFO
ftw.profilehook.egg-info/SOURCES.txt
ftw.profilehook.egg-info/dependency_links.txt
ftw.profilehook.egg-info/entry_points.txt
ftw.profilehook.egg-info/namespace_packages.txt
ftw.profilehook.egg-info/not-zip-safe
ftw.profilehook.egg-info/requires.txt
ftw.profilehook.egg-info/top_level.txt
ftw/profilehook/__init__.py
ftw/profilehook/configure.zcml
ftw/profilehook/interfaces.py
ftw/profilehook/meta.py
ftw/profilehook/meta.zcml
ftw/profilehook/subscribers.py
ftw/profilehook/testing.py
ftw/profilehook/tests/__init__.py
ftw/profilehook/tests/test_integration.py
ftw/profilehook/tests/test_meta_directive.py
ftw/profilehook/tests/profiles/bar/.keep
ftw/profilehook/tests/profiles/foo/.keep