Metadata-Version: 2.1
Name: ftw.profilehook
Version: 1.3.0
Summary: A Plone addon providing a hook for executing code when a generic setup profile is installed.
Home-page: https://github.com/4teamwork/ftw.profilehook
Author: 4teamwork AG
Author-email: mailto:info@4teamwork.ch
License: GPL2
Keywords: ftw generic setup profile hook
Platform: UNKNOWN
Classifier: Environment :: Web Environment
Classifier: Framework :: Plone
Classifier: Framework :: Plone :: 4.3
Classifier: Framework :: Plone :: 5.1
Classifier: Intended Audience :: Developers
Classifier: License :: OSI Approved :: GNU General Public License (GPL)
Classifier: Programming Language :: Python
Classifier: Topic :: Software Development :: Libraries :: Python Modules
Provides-Extra: tests
